cppcontainers/cppcontainers.cpython-38-i386-linux-gnu.so
cppcontainers/__init__.py
cpp_containers-0.1.dist-info/top_level.txt
cpp_containers-0.1.dist-info/METADATA
cpp_containers-0.1.dist-info/LICENSE
cpp_containers-0.1.dist-info/RECORD
cpp_containers-0.1.dist-info/WHEEL
