Metadata-Version: 2.1
Name: cpp-containers
Version: 0.1
Summary: Python wrapper for CPP stdlib containers
Home-page: https://github.com/Dobatymo/cpp-containers-python
Author: Dobatymo
Requires-Python: >=3.6
License-File: LICENSE
